LICENSE
README.md
setup.py
slash_path/__init__.py
slash_path/slash_path.py
slash_path.egg-info/PKG-INFO
slash_path.egg-info/SOURCES.txt
slash_path.egg-info/dependency_links.txt
slash_path.egg-info/top_level.txt