Metadata-Version: 2.1
Name: slash-path
Version: 0.1.1
Summary: use windows path to generate Path object.
Home-page: https://github.com/nutalk/slash_path
Author: Nutalk
Author-email: ht2005112@hotmail.com
License: BSD
Keywords: path
Classifier: Development Status :: 3 - Alpha
Classifier: Topic :: Utilities
Classifier: License :: OSI Approved :: MIT License
Classifier: Programming Language :: Python :: 3
Classifier: Programming Language :: Python :: Implementation :: CPython
License-File: LICENSE
